detection_dataset_annotator/__init__.py
detection_dataset_annotator/about.py
detection_dataset_annotator/desktop.py
detection_dataset_annotator/program.py
detection_dataset_annotator/program_annotator.py
detection_dataset_annotator/program_project.py
detection_dataset_annotator/icons/logo.png
detection_dataset_annotator/modules/__init__.py
detection_dataset_annotator/modules/configure.py
detection_dataset_annotator/modules/wabout.py
detection_dataset_annotator-0.1.8.dist-info/licenses/LICENSE
detection_dataset_annotator-0.1.8.dist-info/METADATA
detection_dataset_annotator-0.1.8.dist-info/WHEEL
detection_dataset_annotator-0.1.8.dist-info/entry_points.txt
detection_dataset_annotator-0.1.8.dist-info/top_level.txt
detection_dataset_annotator-0.1.8.dist-info/RECORD
