Metadata-Version: 2.4
Name: detection_dataset_annotator
Version: 0.1.8
Summary: A slight annotator of detection datasets
Author-email: Fernando Pujaico Rivera <fernando.pujaico.rivera@gmail.com>
Maintainer-email: Fernando Pujaico Rivera <fernando.pujaico.rivera@gmail.com>
License-Expression: GPL-3.0-only WITH Classpath-exception-2.0 OR BSD-3-Clause
Project-URL: Bug Reports, https://github.com/trucomanx/DetectionDatasetAnnotator/issues
Project-URL: Funding, https://trucomanx.github.io/en/funding.html
Project-URL: Documentation, https://github.com/trucomanx/DetectionDatasetAnnotator/tree/main/doc
Project-URL: Source, https://github.com/trucomanx/DetectionDatasetAnnotator
Keywords: dataset,annotator,yolo
Classifier: Programming Language :: Python :: 3
Classifier: Operating System :: OS Independent
Requires-Python: >=3.8
License-File: LICENSE
Requires-Dist: PyQt5
Requires-Dist: GitPython
Requires-Dist: natsort
Dynamic: license-file
